haystack_integrations/components/converters/py.typed
haystack_integrations/components/converters/unstructured/__init__.py
haystack_integrations/components/converters/unstructured/converter.py
unstructured_fileconverter_haystack-1.0.0.dist-info/METADATA
unstructured_fileconverter_haystack-1.0.0.dist-info/WHEEL
unstructured_fileconverter_haystack-1.0.0.dist-info/licenses/LICENSE
unstructured_fileconverter_haystack-1.0.0.dist-info/RECORD
